rfApiTestLibrary/__init__.py
rfApiTestLibrary/activemqLib.py
rfApiTestLibrary/basic.py
rfApiTestLibrary/jsonCompare.py
rfApiTestLibrary/jsonLib.py
rfApiTestLibrary/jsonpath.py
rfApiTestLibrary/junitReportListener.py
rfApiTestLibrary/junitReportListener2.py
rfApiTestLibrary/log.py
rfApiTestLibrary/mysqlLib.py
rfApiTestLibrary/rabitmqLib.py
rfApiTestLibrary/randomUtils.py
rfApiTestLibrary/redisLib.py
rfApiTestLibrary/regularExpressionLib.py
rfApiTestLibrary/requestLib.py
rfApiTestLibrary/rft.py
rfApiTestLibrary/supper.py
rfApiTestLibrary/tmp.py
rfApiTestLibrary/tomlLib.py
rfApiTestLibrary/websocketLib.py
rfApiTestLibrary-0.1.5.data/data/Lib/site-packages/rfApiTestLibrary/keywords/activemq.robot
rfApiTestLibrary-0.1.5.data/data/Lib/site-packages/rfApiTestLibrary/keywords/basic.robot
rfApiTestLibrary-0.1.5.data/data/Lib/site-packages/rfApiTestLibrary/keywords/mysql.robot
rfApiTestLibrary-0.1.5.data/data/Lib/site-packages/rfApiTestLibrary/keywords/rabitmq.robot
rfApiTestLibrary-0.1.5.data/data/Lib/site-packages/rfApiTestLibrary/keywords/random.robot
rfApiTestLibrary-0.1.5.data/data/Lib/site-packages/rfApiTestLibrary/keywords/request.robot
rfApiTestLibrary-0.1.5.data/data/Lib/site-packages/rfApiTestLibrary/keywords/supper.robot
rfApiTestLibrary-0.1.5.data/data/Lib/site-packages/rfApiTestLibrary/keywords/toml.robot
rfApiTestLibrary-0.1.5.data/data/Lib/site-packages/rfApiTestLibrary/keywords/websocket.robot
rfApiTestLibrary-0.1.5.dist-info/METADATA
rfApiTestLibrary-0.1.5.dist-info/WHEEL
rfApiTestLibrary-0.1.5.dist-info/top_level.txt
rfApiTestLibrary-0.1.5.dist-info/RECORD
